[{"name": "Surya Lokesh", "rollNumber": "22B21A4284", "branch": "CSM", "date": "2025-03-06", "time": "21:31:54", "status": "Present"}, {"name": "MADHUSUDHANA RAO", "rollNumber": "22B21A4285", "branch": "CSM", "date": "2025-03-06", "time": "21:31:54", "status": "Absent"}, {"name": "Lokesh", "rollNumber": "22B21A4296", "branch": "CSM", "date": "2025-03-06", "time": "21:31:54", "status": "Absent"}, {"name": "reddy ", "rollNumber": "4293", "branch": "CSM", "date": "2025-03-06", "time": "21:31:54", "status": "Absent"}, {"name": "umesh", "rollNumber": "4295", "branch": "CSM", "date": "2025-03-06", "time": "21:31:54", "status": "Absent"}, {"name": "Surya Lokesh", "rollNumber": "22B21A4284", "branch": "CSM", "date": "2025-03-06", "time": "21:43:20", "status": "Present"}, {"name": "MADHUSUDHANA RAO", "rollNumber": "22B21A4285", "branch": "CSM", "date": "2025-03-06", "time": "21:43:20", "status": "Absent"}, {"name": "Lokesh", "rollNumber": "22B21A4296", "branch": "CSM", "date": "2025-03-06", "time": "21:43:20", "status": "Absent"}, {"name": "reddy ", "rollNumber": "4293", "branch": "CSM", "date": "2025-03-06", "time": "21:43:20", "status": "Absent"}, {"name": "umesh", "rollNumber": "4295", "branch": "CSM", "date": "2025-03-06", "time": "21:43:20", "status": "Absent"}, {"name": "Surya Lokesh", "rollNumber": "22B21A4284", "branch": "CSM", "date": "2025-03-06", "time": "21:44:41", "status": "Absent"}, {"name": "MADHUSUDHANA RAO", "rollNumber": "22B21A4285", "branch": "CSM", "date": "2025-03-06", "time": "21:44:41", "status": "Absent"}, {"name": "Lokesh", "rollNumber": "22B21A4296", "branch": "CSM", "date": "2025-03-06", "time": "21:44:41", "status": "Absent"}, {"name": "reddy ", "rollNumber": "4293", "branch": "CSM", "date": "2025-03-06", "time": "21:44:41", "status": "Present"}, {"name": "umesh", "rollNumber": "4295", "branch": "CSM", "date": "2025-03-06", "time": "21:44:41", "status": "Absent"}, {"name": "Surya Lokesh", "rollNumber": "22B21A4284", "branch": "CSM", "date": "2025-03-06", "time": "21:45:52", "status": "Present"}, {"name": "MADHUSUDHANA RAO", "rollNumber": "22B21A4285", "branch": "CSM", "date": "2025-03-06", "time": "21:45:52", "status": "Absent"}, {"name": "Lokesh", "rollNumber": "22B21A4296", "branch": "CSM", "date": "2025-03-06", "time": "21:45:52", "status": "Absent"}, {"name": "reddy ", "rollNumber": "4293", "branch": "CSM", "date": "2025-03-06", "time": "21:45:52", "status": "Absent"}, {"name": "umesh", "rollNumber": "4295", "branch": "CSM", "date": "2025-03-06", "time": "21:45:52", "status": "Absent"}, {"name": "Surya Lokesh", "rollNumber": "22B21A4284", "branch": "CSM", "date": "2025-03-06", "time": "21:49:13", "status": "Present"}, {"name": "MADHUSUDHANA RAO", "rollNumber": "22B21A4285", "branch": "CSM", "date": "2025-03-06", "time": "21:49:13", "status": "Absent"}, {"name": "Lokesh", "rollNumber": "22B21A4296", "branch": "CSM", "date": "2025-03-06", "time": "21:49:13", "status": "Absent"}, {"name": "reddy ", "rollNumber": "4293", "branch": "CSM", "date": "2025-03-06", "time": "21:49:13", "status": "Absent"}, {"name": "umesh", "rollNumber": "4295", "branch": "CSM", "date": "2025-03-06", "time": "21:49:13", "status": "Absent"}, {"name": "Surya Lokesh", "rollNumber": "22B21A4284", "branch": "CSM", "date": "2025-03-06", "time": "21:51:46", "status": "Present"}, {"name": "MADHUSUDHANA RAO", "rollNumber": "22B21A4285", "branch": "CSM", "date": "2025-03-06", "time": "21:51:46", "status": "Absent"}, {"name": "Lokesh", "rollNumber": "22B21A4296", "branch": "CSM", "date": "2025-03-06", "time": "21:51:46", "status": "Absent"}, {"name": "reddy ", "rollNumber": "4293", "branch": "CSM", "date": "2025-03-06", "time": "21:51:46", "status": "Absent"}, {"name": "umesh", "rollNumber": "4295", "branch": "CSM", "date": "2025-03-06", "time": "21:51:46", "status": "Absent"}, {"name": "Surya Lokesh", "rollNumber": "22B21A4284", "branch": "CSM", "date": "2025-03-06", "time": "21:52:53", "status": "Present"}, {"name": "MADHUSUDHANA RAO", "rollNumber": "22B21A4285", "branch": "CSM", "date": "2025-03-06", "time": "21:52:53", "status": "Present"}, {"name": "Lokesh", "rollNumber": "22B21A4296", "branch": "CSM", "date": "2025-03-06", "time": "21:52:53", "status": "Absent"}, {"name": "reddy ", "rollNumber": "4293", "branch": "CSM", "date": "2025-03-06", "time": "21:52:53", "status": "Absent"}, {"name": "umesh", "rollNumber": "4295", "branch": "CSM", "date": "2025-03-06", "time": "21:52:53", "status": "Absent"}, {"name": "Surya Lokesh", "rollNumber": "22B21A4284", "branch": "CSM", "date": "2025-03-06", "time": "21:53:19", "status": "Present"}, {"name": "MADHUSUDHANA RAO", "rollNumber": "22B21A4285", "branch": "CSM", "date": "2025-03-06", "time": "21:53:19", "status": "Present"}, {"name": "Lokesh", "rollNumber": "22B21A4296", "branch": "CSM", "date": "2025-03-06", "time": "21:53:19", "status": "Absent"}, {"name": "reddy ", "rollNumber": "4293", "branch": "CSM", "date": "2025-03-06", "time": "21:53:19", "status": "Absent"}, {"name": "umesh", "rollNumber": "4295", "branch": "CSM", "date": "2025-03-06", "time": "21:53:19", "status": "Absent"}, {"name": "Surya Lokesh", "rollNumber": "22B21A4284", "branch": "CSM", "date": "2025-03-06", "time": "21:55:51", "status": "Present"}, {"name": "MADHUSUDHANA RAO", "rollNumber": "22B21A4285", "branch": "CSM", "date": "2025-03-06", "time": "21:55:51", "status": "Absent"}, {"name": "Lokesh", "rollNumber": "22B21A4296", "branch": "CSM", "date": "2025-03-06", "time": "21:55:51", "status": "Absent"}, {"name": "reddy ", "rollNumber": "4293", "branch": "CSM", "date": "2025-03-06", "time": "21:55:51", "status": "Absent"}, {"name": "umesh", "rollNumber": "4295", "branch": "CSM", "date": "2025-03-06", "time": "21:55:51", "status": "Absent"}, {"name": "Surya Lokesh", "rollNumber": "22B21A4284", "branch": "CSM", "date": "2025-03-06", "time": "22:12:14", "status": "Absent"}, {"name": "MADHUSUDHANA RAO", "rollNumber": "22B21A4285", "branch": "CSM", "date": "2025-03-06", "time": "22:12:14", "status": "Present"}, {"name": "Lokesh", "rollNumber": "22B21A4296", "branch": "CSM", "date": "2025-03-06", "time": "22:12:14", "status": "Absent"}, {"name": "reddy ", "rollNumber": "4293", "branch": "CSM", "date": "2025-03-06", "time": "22:12:14", "status": "Absent"}, {"name": "umesh", "rollNumber": "4295", "branch": "CSM", "date": "2025-03-06", "time": "22:12:14", "status": "Absent"}, {"name": "Surya Lokesh", "rollNumber": "22B21A4284", "branch": "CSM", "date": "2025-03-06", "time": "22:12:56", "status": "Present"}, {"name": "MADHUSUDHANA RAO", "rollNumber": "22B21A4285", "branch": "CSM", "date": "2025-03-06", "time": "22:12:56", "status": "Absent"}, {"name": "Lokesh", "rollNumber": "22B21A4296", "branch": "CSM", "date": "2025-03-06", "time": "22:12:56", "status": "Absent"}, {"name": "reddy ", "rollNumber": "4293", "branch": "CSM", "date": "2025-03-06", "time": "22:12:56", "status": "Absent"}, {"name": "umesh", "rollNumber": "4295", "branch": "CSM", "date": "2025-03-06", "time": "22:12:56", "status": "Absent"}, {"name": "Surya Lokesh", "rollNumber": "22B21A4284", "branch": "CSM", "date": "2025-03-06", "time": "22:13:58", "status": "Absent"}, {"name": "MADHUSUDHANA RAO", "rollNumber": "22B21A4285", "branch": "CSM", "date": "2025-03-06", "time": "22:13:58", "status": "Present"}, {"name": "Lokesh", "rollNumber": "22B21A4296", "branch": "CSM", "date": "2025-03-06", "time": "22:13:58", "status": "Absent"}, {"name": "reddy ", "rollNumber": "4293", "branch": "CSM", "date": "2025-03-06", "time": "22:13:58", "status": "Absent"}, {"name": "umesh", "rollNumber": "4295", "branch": "CSM", "date": "2025-03-06", "time": "22:13:58", "status": "Absent"}, {"name": "Surya Lokesh", "rollNumber": "22B21A4284", "branch": "CSM", "date": "2025-03-06", "time": "22:14:23", "status": "Present"}, {"name": "MADHUSUDHANA RAO", "rollNumber": "22B21A4285", "branch": "CSM", "date": "2025-03-06", "time": "22:14:23", "status": "Absent"}, {"name": "Lokesh", "rollNumber": "22B21A4296", "branch": "CSM", "date": "2025-03-06", "time": "22:14:23", "status": "Absent"}, {"name": "reddy ", "rollNumber": "4293", "branch": "CSM", "date": "2025-03-06", "time": "22:14:23", "status": "Absent"}, {"name": "umesh", "rollNumber": "4295", "branch": "CSM", "date": "2025-03-06", "time": "22:14:23", "status": "Absent"}, {"name": "Surya Lokesh", "rollNumber": "22B21A4284", "branch": "CSM", "date": "2025-03-06", "time": "22:16:34", "status": "Present"}, {"name": "MADHUSUDHANA RAO", "rollNumber": "22B21A4285", "branch": "CSM", "date": "2025-03-06", "time": "22:16:34", "status": "Absent"}, {"name": "Lokesh", "rollNumber": "22B21A4296", "branch": "CSM", "date": "2025-03-06", "time": "22:16:34", "status": "Absent"}, {"name": "reddy ", "rollNumber": "4293", "branch": "CSM", "date": "2025-03-06", "time": "22:16:34", "status": "Absent"}, {"name": "umesh", "rollNumber": "4295", "branch": "CSM", "date": "2025-03-06", "time": "22:16:34", "status": "Absent"}, {"name": "Surya Lokesh", "rollNumber": "22B21A4284", "branch": "CSM", "date": "2025-03-06", "time": "22:18:10", "status": "Present"}, {"name": "MADHUSUDHANA RAO", "rollNumber": "22B21A4285", "branch": "CSM", "date": "2025-03-06", "time": "22:18:10", "status": "Absent"}, {"name": "Lokesh", "rollNumber": "22B21A4296", "branch": "CSM", "date": "2025-03-06", "time": "22:18:10", "status": "Absent"}, {"name": "reddy ", "rollNumber": "4293", "branch": "CSM", "date": "2025-03-06", "time": "22:18:10", "status": "Absent"}, {"name": "umesh", "rollNumber": "4295", "branch": "CSM", "date": "2025-03-06", "time": "22:18:10", "status": "Absent"}, {"name": "Surya Lokesh", "rollNumber": "22B21A4284", "branch": "CSM", "date": "2025-03-06", "time": "22:18:31", "status": "Present"}, {"name": "MADHUSUDHANA RAO", "rollNumber": "22B21A4285", "branch": "CSM", "date": "2025-03-06", "time": "22:18:31", "status": "Absent"}, {"name": "Lokesh", "rollNumber": "22B21A4296", "branch": "CSM", "date": "2025-03-06", "time": "22:18:31", "status": "Absent"}, {"name": "reddy ", "rollNumber": "4293", "branch": "CSM", "date": "2025-03-06", "time": "22:18:31", "status": "Absent"}, {"name": "umesh", "rollNumber": "4295", "branch": "CSM", "date": "2025-03-06", "time": "22:18:31", "status": "Absent"}, {"name": "Surya Lokesh", "rollNumber": "22B21A4284", "branch": "CSM", "date": "2025-03-06", "time": "22:21:08", "status": "Present"}, {"name": "MADHUSUDHANA RAO", "rollNumber": "22B21A4285", "branch": "CSM", "date": "2025-03-06", "time": "22:21:08", "status": "Present"}, {"name": "Lokesh", "rollNumber": "22B21A4296", "branch": "CSM", "date": "2025-03-06", "time": "22:21:08", "status": "Absent"}, {"name": "reddy ", "rollNumber": "4293", "branch": "CSM", "date": "2025-03-06", "time": "22:21:08", "status": "Absent"}, {"name": "umesh", "rollNumber": "4295", "branch": "CSM", "date": "2025-03-06", "time": "22:21:08", "status": "Absent"}, {"name": "Surya Lokesh", "rollNumber": "22B21A4284", "branch": "CSM", "date": "2025-03-06", "time": "22:21:49", "status": "Present"}, {"name": "MADHUSUDHANA RAO", "rollNumber": "22B21A4285", "branch": "CSM", "date": "2025-03-06", "time": "22:21:49", "status": "Present"}, {"name": "Lokesh", "rollNumber": "22B21A4296", "branch": "CSM", "date": "2025-03-06", "time": "22:21:49", "status": "Present"}, {"name": "reddy ", "rollNumber": "4293", "branch": "CSM", "date": "2025-03-06", "time": "22:21:49", "status": "Absent"}, {"name": "umesh", "rollNumber": "4295", "branch": "CSM", "date": "2025-03-06", "time": "22:21:49", "status": "Absent"}, {"name": "Surya Lokesh", "rollNumber": "22B21A4284", "branch": "CSM", "date": "2025-03-06", "time": "22:24:37", "status": "Absent"}, {"name": "MADHUSUDHANA RAO", "rollNumber": "22B21A4285", "branch": "CSM", "date": "2025-03-06", "time": "22:24:37", "status": "Absent"}, {"name": "Lokesh", "rollNumber": "22B21A4296", "branch": "CSM", "date": "2025-03-06", "time": "22:24:37", "status": "Absent"}, {"name": "reddy ", "rollNumber": "4293", "branch": "CSM", "date": "2025-03-06", "time": "22:24:37", "status": "Absent"}, {"name": "umesh", "rollNumber": "4295", "branch": "CSM", "date": "2025-03-06", "time": "22:24:37", "status": "Absent"}, {"name": "Surya Lokesh", "rollNumber": "22B21A4284", "branch": "CSM", "date": "2025-03-06", "time": "22:26:06", "status": "Present"}, {"name": "MADHUSUDHANA RAO", "rollNumber": "22B21A4285", "branch": "CSM", "date": "2025-03-06", "time": "22:26:06", "status": "Absent"}, {"name": "Lokesh", "rollNumber": "22B21A4296", "branch": "CSM", "date": "2025-03-06", "time": "22:26:06", "status": "Absent"}, {"name": "reddy ", "rollNumber": "4293", "branch": "CSM", "date": "2025-03-06", "time": "22:26:06", "status": "Absent"}, {"name": "umesh", "rollNumber": "4295", "branch": "CSM", "date": "2025-03-06", "time": "22:26:06", "status": "Absent"}, {"name": "Surya Lokesh", "rollNumber": "22B21A4284", "branch": "CSM", "date": "2025-03-06", "time": "22:27:55", "status": "Present"}, {"name": "MADHUSUDHANA RAO", "rollNumber": "22B21A4285", "branch": "CSM", "date": "2025-03-06", "time": "22:27:55", "status": "Absent"}, {"name": "Lokesh", "rollNumber": "22B21A4296", "branch": "CSM", "date": "2025-03-06", "time": "22:27:55", "status": "Absent"}, {"name": "reddy ", "rollNumber": "4293", "branch": "CSM", "date": "2025-03-06", "time": "22:27:55", "status": "Absent"}, {"name": "umesh", "rollNumber": "4295", "branch": "CSM", "date": "2025-03-06", "time": "22:27:55", "status": "Absent"}, {"name": "Surya Lokesh", "rollNumber": "22B21A4284", "branch": "CSM", "date": "2025-03-06", "status": "Absent"}, {"name": "MADHUSUDHANA RAO", "rollNumber": "22B21A4285", "branch": "CSM", "date": "2025-03-06", "status": "Present"}, {"name": "Lokesh", "rollNumber": "22B21A4296", "branch": "CSM", "date": "2025-03-06", "status": "Present"}, {"name": "reddy ", "rollNumber": "4293", "branch": "CSM", "date": "2025-03-06", "status": "Absent"}, {"name": "umesh", "rollNumber": "4295", "branch": "CSM", "date": "2025-03-06", "status": "Absent"}, {"name": "Surya Lokesh", "rollNumber": "22B21A4284", "branch": "CSM", "date": "2025-03-06", "time": "22:43:13", "status": "Absent"}, {"name": "MADHUSUDHANA RAO", "rollNumber": "22B21A4285", "branch": "CSM", "date": "2025-03-06", "time": "22:43:13", "status": "Present"}, {"name": "Lokesh", "rollNumber": "22B21A4296", "branch": "CSM", "date": "2025-03-06", "time": "22:43:13", "status": "Present"}, {"name": "reddy ", "rollNumber": "4293", "branch": "CSM", "date": "2025-03-06", "time": "22:43:13", "status": "Present"}, {"name": "umesh", "rollNumber": "4295", "branch": "CSM", "date": "2025-03-06", "time": "22:43:13", "status": "Absent"}, {"name": "Surya Lokesh", "rollNumber": "22B21A4284", "branch": "CSM", "date": "2025-03-06", "time": "23:04:03", "status": "Present"}, {"name": "MADHUSUDHANA RAO", "rollNumber": "22B21A4285", "branch": "CSM", "date": "2025-03-06", "time": "23:04:03", "status": "Present"}, {"name": "Lokesh", "rollNumber": "22B21A4296", "branch": "CSM", "date": "2025-03-06", "time": "23:04:03", "status": "Absent"}, {"name": "reddy ", "rollNumber": "4293", "branch": "CSM", "date": "2025-03-06", "time": "23:04:03", "status": "Absent"}, {"name": "umesh", "rollNumber": "4295", "branch": "CSM", "date": "2025-03-06", "time": "23:04:03", "status": "Absent"}, {"name": "Surya Lokesh", "rollNumber": "22B21A4284", "branch": "CSM", "date": "2025-03-06", "time": "23:07:09", "status": "Present"}, {"name": "MADHUSUDHANA RAO", "rollNumber": "22B21A4285", "branch": "CSM", "date": "2025-03-06", "time": "23:07:09", "status": "Present"}, {"name": "Lokesh", "rollNumber": "22B21A4296", "branch": "CSM", "date": "2025-03-06", "time": "23:07:09", "status": "Absent"}, {"name": "reddy ", "rollNumber": "4293", "branch": "CSM", "date": "2025-03-06", "time": "23:07:09", "status": "Absent"}, {"name": "umesh", "rollNumber": "4295", "branch": "CSM", "date": "2025-03-06", "time": "23:07:09", "status": "Absent"}, {"name": "Surya Lokesh", "rollNumber": "22B21A4284", "branch": "CSM", "date": "2025-03-06", "time": "23:08:01", "status": "Absent"}, {"name": "MADHUSUDHANA RAO", "rollNumber": "22B21A4285", "branch": "CSM", "date": "2025-03-06", "time": "23:08:01", "status": "Present"}, {"name": "Lokesh", "rollNumber": "22B21A4296", "branch": "CSM", "date": "2025-03-06", "time": "23:08:01", "status": "Present"}, {"name": "reddy ", "rollNumber": "4293", "branch": "CSM", "date": "2025-03-06", "time": "23:08:01", "status": "Absent"}, {"name": "umesh", "rollNumber": "4295", "branch": "CSM", "date": "2025-03-06", "time": "23:08:01", "status": "Absent"}, {"name": "Surya Lokesh", "rollNumber": "22B21A4284", "branch": "CSM", "date": "2025-03-06", "time": "23:17:09", "status": "Present"}]